registrable/__init__.py
registrable/exceptions.py
registrable/version.py
registrable/tests/__init__.py
registrable/tests/registrable_test.py
registrable-0.0.4.dist-info/LICENSE
registrable-0.0.4.dist-info/METADATA
registrable-0.0.4.dist-info/WHEEL
registrable-0.0.4.dist-info/top_level.txt
registrable-0.0.4.dist-info/RECORD
