Metadata-Version: 2.1
Name: registrable
Version: 0.0.4
Summary: Python module for registering and instantiating classes by name. Based on the implementation from AllenNLP.
Home-page: https://github.com/epwalsh/python-registrable
Author: Evan Pete Walsh
Author-email: epwalsh10@gmail.com
License: Apache 2.0
Platform: UNKNOWN
Classifier: Intended Audience :: Developers
Classifier: Development Status :: 3 - Alpha
Classifier: License :: OSI Approved :: Apache Software License
Classifier: Operating System :: OS Independent
Classifier: Programming Language :: Python :: 3.6
Classifier: Programming Language :: Python :: 3.7
Classifier: Programming Language :: Python :: 3.8
Requires-Python: >=3.6.1
